etl_pipeline_runner-3.0.1.dist-info/METADATA
etl_pipeline_runner-3.0.1.dist-info/WHEEL
etl_pipeline_runner-3.0.1.dist-info/licenses/LICENSE
etl_pipeline_runner/__init__.py
etl_pipeline_runner/services.py
etl_pipeline_runner-3.0.1.dist-info/RECORD
