Metadata-Version: 2.1
Name: etl-pipeline-runner
Version: 3.0.1
Summary: A package to run ETL Pipeline
Author-Email: Md Badiuzzaman Pranto <prantoamt@gmail.com>
License: MIT
Requires-Python: >=3.10
Requires-Dist: attrs>=23.1.0
Requires-Dist: greenlet>=3.0.1
Requires-Dist: iniconfig>=2.0.0
Requires-Dist: pandas>=2.1.3
Requires-Dist: packaging>=23.2
Requires-Dist: pluggy>=1.3.0
Requires-Dist: python-dateutil>=2.8.2
Requires-Dist: pytz>=2023.3.post1
Requires-Dist: six>=1.16.0
Requires-Dist: SQLAlchemy>=2.0.23
Requires-Dist: typing-extensions>=4.8.0
Requires-Dist: opendatasets>=0.1.22
Requires-Dist: tqdm>=4.66.1
